{
  "_id": {
    "$oid": "1"
  },
  "username": "SrPino23",
  "mail": "omgalexis570@gmail.com",
  "password": "192834@pinotech",
  "folders": [
    {
      "name": "Folder 1",
      "rute": "",
      "mainFolder": "1",
      "files": [
        {
          "name": "Image 1.jpg",
          "size": "101944",
          "extension": ".jpg",
          "rute": "http://pinotech.v6.army/files/Files/fotoEjemplo.png",
          "url": "",
          "_id": {
            "$oid": "2"
          }
        },
        {
          "name": "Image 2.jpg",
          "size": "101944",
          "extension": ".jpg",
          "rute": "http://pinotech.v6.army/files/Files/fotoEjemplo.png",
          "url": "",
          "_id": {
            "$oid": "3"
          }
        }
      ],
      "folders": [
        {
          "name": "Folder 2",
          "rute": "",
          "mainFolder": "6",
          "files": [],
          "folders": [],
          "_id": {
            "$oid": "4"
          },
          "date": {
            "$date": "2024-03-23"
          }
        },
        {
          "name": "Folder 3",
          "rute": "",
          "mainFolder": "6",
          "files": [],
          "folders": [],
          "_id": {
            "$oid": "5"
          },
          "date": {
            "$date": "2024-03-23"
          }
        }
      ],
      "_id": {
        "$oid": "6"
      },
      "date": {
        "$date": "2024-03-23"
      }
    },
    {
      "name": "Folder 4",
      "rute": "",
      "mainFolder": "1",
      "files": [
        {
          "name": "Image 3.jpg",
          "size": "101944",
          "extension": ".jpg",
          "rute": "http://pinotech.v6.army/files/Files/fotoEjemplo.png",
          "url": "",
          "_id": {
            "$oid": "7"
          }
        }
      ],
      "folders": [
        {
          "name": "Folder 5",
          "rute": "",
          "mainFolder": "14",
          "files": [
          ],
          "folders": [
            {
              "name": "Folder 6",
              "rute": "",
              "mainFolder": "13",
              "files": [
                {
                  "name": "Virus.exe",
                  "size": "8000000000000",
                  "extension": ".jpg",
                  "rute": "http://pinotech.v6.army/files/Files/virusBroma.png",
                  "url": "",
                  "_id": {
                    "$oid": "8"
                  }
                },
                {
                  "name": "Porque entraste?",
                  "size": "8000000000000",
                  "extension": ".jpg",
                  "rute": "http://pinotech.v6.army/files/Files/virusBroma.png",
                  "url": "",
                  "_id": {
                    "$oid": "9"
                  }
                },
                {
                  "name": "Estas perdido",
                  "size": "8000000000000",
                  "extension": ".jpg",
                  "rute": "http://pinotech.v6.army/files/Files/virusBroma.png",
                  "url": "",
                  "_id": {
                    "$oid": "10"
                  }
                },
                {
                  "name": "¡Sal de aqui ahora!",
                  "size": "8000000000000",
                  "extension": ".jpg",
                  "rute": "http://pinotech.v6.army/files/Files/virusBroma.png",
                  "url": "",
                  "_id": {
                    "$oid": "11"
                  }
                }
              ],
              "folders": [
              ],
              "_id": {
                "$oid": "12"
              },
              "date": {
                "$date": "2024-03-23"
              }
            }
          ],
          "_id": {
            "$oid": "13"
          },
          "date": {
            "$date": "2024-03-23"
          }
        }
      ],
      "_id": {
        "$oid": "14"
      },
      "date": {
        "$date": "2024-03-23"
      }
    },
    {
      "name": "Folder 5",
      "rute": "",
      "mainFolder": "1",
      "files": [],
      "folders": [],
      "_id": {
        "$oid": "15"
      },
      "date": {
        "$date": "2024-03-23"
      }
    }
  ],
  "files": [
    {
      "name": "Image 5.jpg",
      "size": "101944",
      "extension": ".jpg",
      "rute": "http://pinotech.v6.army/files/Files/fotoEjemplo.png",
      "url": "",
      "_id": {
        "$oid": "16"
      }
    },
    {
      "name": "Image 6.jpg",
      "size": "101944",
      "extension": ".jpg",
      "rute": "http://pinotech.v6.army/files/Files/fotoEjemplo.png",
      "url": "",
      "_id": {
        "$oid": "17"
      }
    },
    {
      "name": "Document 1 aaaaaa.docx",
      "size": "2221944",
      "extension": ".docx",
      "rute": "http://pinotech.v6.army/files/Files/fotoEjemplo.png",
      "url": "",
      "_id": {
        "$oid": "18"
      }
    }
  ],
  "date": {
    "$date": "2024-03-23"
  }
}
